MANIFEST.in
Makefile
README.txt
setup.py
digipy/__init__.py
digipy/app.py
digipy/campui_gui.py
digipy/compare_raw_FE.py
digipy/data_analysis_freq.py
digipy/digits_all.csv
digipy/digits_all.save
digipy/digits_opt.save
digipy/digits_raw.save
digipy/digits_simple.save
digipy/extract_features.py
digipy/features_2d.py
digipy/image_util.py
digipy/mean_digits.txt
digipy/nn.save
digipy/pkg_util.py
digipy/see_sample_digits.py
digipy/test.save
digipy/train.py
digipy.egg-info/PKG-INFO
digipy.egg-info/SOURCES.txt
digipy.egg-info/dependency_links.txt
digipy.egg-info/entry_points.txt
digipy.egg-info/requires.txt
digipy.egg-info/top_level.txt
digipy/datasets/__init__.py
digipy/datasets/digits/__init__.py
digipy/datasets/digits/digits-test.csv
digipy/datasets/digits/digits-train.csv
digipy/datasets/digits/digits-train.data
digipy/datasets/digits/digits.csv
digipy/datasets/digits/digits.data
digipy/datasets/digits/fe-digits-all.csv
digipy/datasets/digits/fe-digits-all.data
digipy/datasets/digits/fe-digits-opt.csv
digipy/datasets/digits/fe-digits-opt.data
digipy/datasets/digits/fe-digits-simple.csv
digipy/datasets/digits/fe-digits-simple.data
digipy/datasets/digits/fe-digits-start-stop.data
digipy/datasets/digits/fe-digits-train.data
digipy/datasets/digits/fe-digits-volume.data
digipy/datasets/digits/test.py
digipy/datasets/digits/test.save
digipy/ui/__init__.py
digipy/ui/campui_gui.ui
digipy/ui/ui_campui_gui.py