Metadata-Version: 1.0
Name: digipy
Version: 0.1.1
Summary: A cool demo for Montreal Python 6 that does real time digits recognition
Home-page: UNKNOWN
Author: Francis Pieraut
Author-email: fpieraut@gmail.com
License: AGPL v3 or later
Platform: UNKNOWN
